.gitignore
.travis.yml
LICENSE
MANIFEST.in
README.rst
setup.cfg
setup.py
tox.ini
stackbench/__init__.py
stackbench.egg-info/PKG-INFO
stackbench.egg-info/SOURCES.txt
stackbench.egg-info/dependency_links.txt
stackbench.egg-info/requires.txt
stackbench.egg-info/top_level.txt
stackbench/api/__init__.py
stackbench/api/auth.py
stackbench/api/client.py
stackbench/api/exceptions.py
stackbench/api/factory.py
stackbench/api/util.py
stackbench/cloud/__init__.py
stackbench/cloud/base.py
stackbench/cloud/ec2.py
stackbench/cloud/exceptions.py
stackbench/cloud/factory.py
stackbench/cloud/gce.py
stackbench/fio/__init__.py
stackbench/fio/engine.py
stackbench/fio/exceptions.py
stackbench/fio/output.py
stackbench/fio/config/__init__.py
stackbench/fio/config/config.py
stackbench/fio/config/job.py
stackbench/fio/config/library.py
stackbench/fio/report/__init__.py
stackbench/fio/report/single.py
stackbench/test/__init__.py
stackbench/test/utils.py
stackbench/test/api/__init__.py
stackbench/test/api/test_auth.py
stackbench/test/api/test_create.py
stackbench/test/api/test_errors.py
stackbench/test/api/test_get.py
stackbench/test/api/test_list.py
stackbench/test/cloud/__init__.py
stackbench/test/cloud/test_ec2.py
stackbench/test/cloud/test_gce.py
stackbench/test/cloud/test_identify.py
stackbench/test/cloud/test_utils.py
stackbench/test/fio/__init__.py
stackbench/test/fio/test_config.py
stackbench/test/fio/test_engine.py
stackbench/test/fio/test_output.py
stackbench/test/fio/test_report.py
stackbench/utils/__init__.py
stackbench/utils/daemon.py
stackbench/utils/fs.py